Workbook
Name Праздники: OFFSET(Праздники!$A$1,0,0,COUNTA(Праздники!$A$1:$A$21),1)

Sheet TaskList
C1: Календарный график проекта
C3: Дата начала проекта | E3: 46113 | F3: FALSE
C4: Дата окончания проекта | E4: 46296 | I4: Responsible - ответственный исполнитель | J4: Accountable - владелец результата (приемка задачи) | K4: Consulted - консультант/ эксперт | L4: Informed - Информируемый
C5: Шаг временной шкалы (дней/клетку) | E5: 1
J7: Accountable - владелец результата (приемка задачи) | K7: Consulted - консультант/ эксперт | L7: Informed - Информируемый | P7: =IF(P8=TODAY(),CHAR(113),"") | Q7: =IF(Q8=TODAY(),CHAR(113),"") | R7: =IF(R8=TODAY(),CHAR(113),"") | S7: =IF(S8=TODAY(),CHAR(113),"") | T7: =IF(T8=TODAY(),CHAR(113),"") | U7: =IF(U8=TODAY(),CHAR(113),"") | V7: =IF(V8=TODAY(),CHAR(113),"") | W7: =IF(W8=TODAY(),CHAR(113),"") | ... EX7: =IF(EX8=TODAY(),CHAR(113),"")
B8: № | C8: Этап | D8: Ответственный | E8: Начало этапа | F8: =IF(F3,"Длительность, раб.дн.","Длительность, дн.") -> Длительность, дн. | G8: Конец этапа | H8: % выполнения | I8: R | J8: A | K8: C | L8: I | M8: Подтверждение результата | N8: Nex steps | O8: Комментарий | P8: =E3 -> 46113 | Q8: =IF(P8<=$E$4,P8+$E$5,"") -> 46114 | R8: =IF(Q8<=$E$4,Q8+$E$5,"") -> 46115 | S8: =IF(R8<=$E$4,R8+$E$5,"") -> 46116 | T8: =IF(S8<=$E$4,S8+$E$5,"") -> 46117 | U8: =IF(T8<=$E$4,T8+$E$5,"") -> 46118 | V8: =IF(U8<=$E$4,U8+$E$5,"") -> 46119 | W8: =IF(V8<=$E$4,V8+$E$5,"") -> 46120 | X8: =IF(W8<=$E$4,W8+$E$5,"") -> 46121 | ... IR8: =IF(IQ8<=$E$4,IQ8+$E$5,"")
B9: 1. Бизнес-анализ и описание требований | E9: 46113 | F9: =NETWORKDAYS(E9,G9,Праздники!$A$1:$A$14) -> 27 | G9: 46150 | H9: =AVERAGE(H10:H26) -> 0.79642857 | P9: =IF(P$8=TODAY(),CHAR(124),"") | Q9: =IF(Q$8=TODAY(),CHAR(124),"") | R9: =IF(R$8=TODAY(),CHAR(124),"") | S9: =IF(S$8=TODAY(),CHAR(124),"") | T9: =IF(T$8=TODAY(),CHAR(124),"") | U9: =IF(U$8=TODAY(),CHAR(124),"") | V9: =IF(V$8=TODAY(),CHAR(124),"") | W9: =IF(W$8=TODAY(),CHAR(124),"") | ... EX9: =IF(EX$8=TODAY(),CHAR(124),"")
B10: 1.1 | C10: Описание бизнес-процессов в части HC Tracker и HCMC forms | D10: А. Колесов | E10: 46113 | F10: =NETWORKDAYS(E10,G10,Праздники!$A$1:$A$14) -> 22 | G10: 46142 | H10: 1 | I10: AKol | J10: VD | K10: EA, YuR | L10: EA, YuR, Akor | M10: Бизнес-анализ HC Tracker и HCMC.docx | P10: =IF(P$8=TODAY(),CHAR(124),"") | Q10: =IF(Q$8=TODAY(),CHAR(124),"") | R10: =IF(R$8=TODAY(),CHAR(124),"") | S10: =IF(S$8=TODAY(),CHAR(124),"") | T10: =IF(T$8=TODAY(),CHAR(124),"") | U10: =IF(U$8=TODAY(),CHAR(124),"") | V10: =IF(V$8=TODAY(),CHAR(124),"") | W10: =IF(W$8=TODAY(),CHAR(124),"") | ... EX10: =IF(EX$8=TODAY(),CHAR(124),"")
B11: 1.2 | C11: Анализ HCMC форм | D11: А. Коршунов | E11: 46141 | F11: =NETWORKDAYS(E11,G11,Праздники!$A$1:$A$14) -> 5 | G11: 46148 | H11: 1 | I11: AKor | P11: =IF(P$8=TODAY(),CHAR(124),"") | Q11: =IF(Q$8=TODAY(),CHAR(124),"") | R11: =IF(R$8=TODAY(),CHAR(124),"") | S11: =IF(S$8=TODAY(),CHAR(124),"") | T11: =IF(T$8=TODAY(),CHAR(124),"") | U11: =IF(U$8=TODAY(),CHAR(124),"") | V11: =IF(V$8=TODAY(),CHAR(124),"") | W11: =IF(W$8=TODAY(),CHAR(124),"") | ... EX11: =IF(EX$8=TODAY(),CHAR(124),"")
B12: 1.3 | C12: Альбом/описание бюджетных форм | D12: Лена, Юра, Женя | E12: 46133 | F12: =NETWORKDAYS(E12,G12,Праздники!$A$1:$A$14) -> 6 | G12: 46140 | H12: 1 | I12: EE, YuR | K12: EA | L12: EA | P12: =IF(P$8=TODAY(),CHAR(124),"") | Q12: =IF(Q$8=TODAY(),CHAR(124),"") | R12: =IF(R$8=TODAY(),CHAR(124),"") | S12: =IF(S$8=TODAY(),CHAR(124),"") | T12: =IF(T$8=TODAY(),CHAR(124),"") | U12: =IF(U$8=TODAY(),CHAR(124),"") | V12: =IF(V$8=TODAY(),CHAR(124),"") | W12: =IF(W$8=TODAY(),CHAR(124),"") | ... EX12: =IF(EX$8=TODAY(),CHAR(124),"")
B13: 1.3.1 | C13: Аудит и актуализация альбома бюджетных форм - Кроме Банка | E13: 46269 | F13: =NETWORKDAYS(E13,G13,Праздники!$A$1:$A$14) -> 6 | G13: 46276 | H13: 0.1 | I13: YuR, AO, EE | J13: YuR, EE | K13: EA
B14: 1.3.1 | C14: Аудит и актуализация альбома бюджетных форм - Банковская | E14: 46269 | F14: =NETWORKDAYS(E14,G14,Праздники!$A$1:$A$14) -> 6 | G14: 46276 | H14: 1 | I14: EE | J14: EE | K14: EA | L14: AO, YuR | N14: прислать ссылку на формы
B15: 1.4 | C15: Альбом/описание отчетных форм | D15: Лена, Юра, Женя | E15: 46133 | F15: =NETWORKDAYS(E15,G15,Праздники!$A$1:$A$14) -> 6 | G15: 46140 | H15: 1 | I15: EE, YuR | J15: DZh | K15: EA | L15: Ea, SO | P15: =IF(P$8=TODAY(),CHAR(124),"") | Q15: =IF(Q$8=TODAY(),CHAR(124),"") | R15: =IF(R$8=TODAY(),CHAR(124),"") | S15: =IF(S$8=TODAY(),CHAR(124),"") | T15: =IF(T$8=TODAY(),CHAR(124),"") | U15: =IF(U$8=TODAY(),CHAR(124),"") | V15: =IF(V$8=TODAY(),CHAR(124),"") | W15: =IF(W$8=TODAY(),CHAR(124),"") | ... EX15: =IF(EX$8=TODAY(),CHAR(124),"")
B16: 1.4.1 | C16: Аудит и актуализация альбома отчетных форм - Кроме Банка | E16: 46269 | F16: =NETWORKDAYS(E16,G16,Праздники!$A$1:$A$14) -> 6 | G16: 46276 | H16: 0.1 | I16: YuR, AO, EE | J16: YuR, EE | K16: EA
B17: 1.4.1.1 | C17: Форма 1.1_план-факт ФОТ | D17: Лена, Юра, Женя | E17: 46133 | F17: =NETWORKDAYS(E17,G17,Праздники!$A$1:$A$14) -> 6 | G17: 46140 | H17: 1 | I17: YuR | J17: DZh | K17: EE, AO, EA, VD | L17: EE, AO, EA, VD | M17: Форма 1_План-факт ФОТ
B18: 1.4.1.2 | C18: Форма 1.2_Waterfall по факторному анализу
B19: 1.4.1.3 | C19: Форма 3
B20: 1.4.1.4 | C20: Форма 4 и тд
B21: 1.4.1.5 | C21: Набор отчетных форм по HC Tracker | E21: 46133 | F21: =NETWORKDAYS(E21,G21,Праздники!$A$1:$A$14) -> 6 | G21: 46140 | H21: 1 | I21: YuR | J21: YuR | L21: HR Advisory
B22: 1.4.2 | C22: Аудит и актуализация альбома отчетных форм - Банковская | E22: 46269 | F22: =NETWORKDAYS(E22,G22,Праздники!$A$1:$A$14) -> 6 | G22: 46276 | H22: 1 | I22: EE | J22: EE | K22: EA | L22: AO, YuR
B23: 5 | C23: Детальное описание форм | D23: Аня | E23: 46189 | F23: =NETWORKDAYS(E23,G23,Праздники!$A$1:$A$14) -> 64 | G23: 46276 | H23: 0.5 | I23: AO | K23: EE, YuR, EA | O23: Описание методологии подготовки бюджетных и отчетных форм (в т.ч. Accruals и тд)
B24: 6 | C24: Описание/макеты Бюджетных/Comp Dashboards | D24: Лена, Юра, Женя | E24: 46154 | F24: =NETWORKDAYS(E24,G24,Праздники!$A$1:$A$14) -> 100 | G24: 46294 | H24: 0.5 | I24: EE, YuR, EA, AO | J24: DZh | N24: Провести встречу по оценке возможностей реализации дашбордов - приоритеты и сроки
B25: 7 | C25: Разработка пользовательских сценариев для HC Tracker и HCMC forms | D25: А. Колесов | E25: 46146 | F25: =NETWORKDAYS(E25,G25,Праздники!$A$1:$A$14) -> 9 | G25: 46158 | H25: 1 | I25: AKol | J25: VD, AO | L25: VD, AO, YuR | M25: Пользовательские сценарии.docx | P25: =IF(P$8=TODAY(),CHAR(124),"") | Q25: =IF(Q$8=TODAY(),CHAR(124),"") | R25: =IF(R$8=TODAY(),CHAR(124),"") | S25: =IF(S$8=TODAY(),CHAR(124),"") | T25: =IF(T$8=TODAY(),CHAR(124),"") | U25: =IF(U$8=TODAY(),CHAR(124),"") | V25: =IF(V$8=TODAY(),CHAR(124),"") | W25: =IF(W$8=TODAY(),CHAR(124),"") | ... EX25: =IF(EX$8=TODAY(),CHAR(124),"")
B26: =B25+1 -> 8 | C26: Мэппинг статей затрат | D26: Юра, Лена | E26: 46146 | F26: =NETWORKDAYS(E26,G26,Праздники!$A$1:$A$14) -> 93 | G26: 46276 | H26: 0.95 | I26: YuR | J26: YuR | K26: VD | M26: Реализация в 1С в разделе "Учет ЦБ" -> Мэппинг счетов МСФО | P26: =IF(P$8=TODAY(),CHAR(124),"") | Q26: =IF(Q$8=TODAY(),CHAR(124),"") | R26: =IF(R$8=TODAY(),CHAR(124),"") | S26: =IF(S$8=TODAY(),CHAR(124),"") | T26: =IF(T$8=TODAY(),CHAR(124),"") | U26: =IF(U$8=TODAY(),CHAR(124),"") | V26: =IF(V$8=TODAY(),CHAR(124),"") | W26: =IF(W$8=TODAY(),CHAR(124),"") | ... EX26: =IF(EX$8=TODAY(),CHAR(124),"")
B27: результат | C27: Описаны бизнес-процессы, формы, пользовательские сценарии | D27: Вася | E27: 46150 | F27: =NETWORKDAYS(E27,G27,Праздники!$A$1:$A$14) -> 1 | G27: 46150 | H27: 1 | I27: VD | P27: =IF(P$8=TODAY(),CHAR(124),"") | Q27: =IF(Q$8=TODAY(),CHAR(124),"") | R27: =IF(R$8=TODAY(),CHAR(124),"") | S27: =IF(S$8=TODAY(),CHAR(124),"") | T27: =IF(T$8=TODAY(),CHAR(124),"") | U27: =IF(U$8=TODAY(),CHAR(124),"") | V27: =IF(V$8=TODAY(),CHAR(124),"") | W27: =IF(W$8=TODAY(),CHAR(124),"") | ... EX27: =IF(EX$8=TODAY(),CHAR(124),"")
B28: 2. Проектирование | E28: 46132 | F28: =NETWORKDAYS(E28,G28,Праздники!$A$1:$A$14) -> 18 | G28: 46157 | P28: =IF(P$8=TODAY(),CHAR(124),"") | Q28: =IF(Q$8=TODAY(),CHAR(124),"") | R28: =IF(R$8=TODAY(),CHAR(124),"") | S28: =IF(S$8=TODAY(),CHAR(124),"") | T28: =IF(T$8=TODAY(),CHAR(124),"") | U28: =IF(U$8=TODAY(),CHAR(124),"") | V28: =IF(V$8=TODAY(),CHAR(124),"") | W28: =IF(W$8=TODAY(),CHAR(124),"") | ... EX28: =IF(EX$8=TODAY(),CHAR(124),"")
B29: 2.1. | C29: Разработка архитектуры решения | D29: Вася | E29: 46139 | F29: =NETWORKDAYS(E29,G29,Праздники!$A$1:$A$14) -> 6 | G29: 46147 | H29: 1 | I29: VD | P29: =IF(P$8=TODAY(),CHAR(124),"") | Q29: =IF(Q$8=TODAY(),CHAR(124),"") | R29: =IF(R$8=TODAY(),CHAR(124),"") | S29: =IF(S$8=TODAY(),CHAR(124),"") | T29: =IF(T$8=TODAY(),CHAR(124),"") | U29: =IF(U$8=TODAY(),CHAR(124),"") | V29: =IF(V$8=TODAY(),CHAR(124),"") | W29: =IF(W$8=TODAY(),CHAR(124),"") | ... EX29: =IF(EX$8=TODAY(),CHAR(124),"")
B30: 2.2. | C30: Разработка моделей данных | E30: 46132 | F30: =NETWORKDAYS(E30,G30,Праздники!$A$1:$A$14) -> 104 | G30: =MAX(G31:G35) -> 46280 | H30: =AVERAGE(H31:H35) -> 0.74 | P30: =IF(P$8=TODAY(),CHAR(124),"") | Q30: =IF(Q$8=TODAY(),CHAR(124),"") | R30: =IF(R$8=TODAY(),CHAR(124),"") | S30: =IF(S$8=TODAY(),CHAR(124),"") | T30: =IF(T$8=TODAY(),CHAR(124),"") | U30: =IF(U$8=TODAY(),CHAR(124),"") | V30: =IF(V$8=TODAY(),CHAR(124),"") | W30: =IF(W$8=TODAY(),CHAR(124),"") | ... EX30: =IF(EX$8=TODAY(),CHAR(124),"")
B31: 2.2.1. | C31: HC трекер | D31: Женя | E31: 46132 | F31: =NETWORKDAYS(E31,G31,Праздники!$A$1:$A$14) -> 14 | G31: 46150 | H31: 1 | I31: EA | J31: VD | M31: HC_TRACKER_ER_Diagramm | P31: =IF(P$8=TODAY(),CHAR(124),"") | Q31: =IF(Q$8=TODAY(),CHAR(124),"") | R31: =IF(R$8=TODAY(),CHAR(124),"") | S31: =IF(S$8=TODAY(),CHAR(124),"") | T31: =IF(T$8=TODAY(),CHAR(124),"") | U31: =IF(U$8=TODAY(),CHAR(124),"") | V31: =IF(V$8=TODAY(),CHAR(124),"") | W31: =IF(W$8=TODAY(),CHAR(124),"") | ... EX31: =IF(EX$8=TODAY(),CHAR(124),"")
B32: 2.2.1. | C32: HC трекер - доработки после тестирования | E32: 46258 | F32: =NETWORKDAYS(E32,G32,Праздники!$A$1:$A$14) -> 10 | G32: 46269 | H32: 0.3 | I32: EA | J32: VD | N32: Last changes Update
B33: 2.2.2. | C33: HCMC | D33: Вася, А. Коршунов | E33: 46149 | F33: =NETWORKDAYS(E33,G33,Праздники!$A$1:$A$14) -> 2 | G33: 46150 | H33: 1 | I33: VD, AKor | P33: =IF(P$8=TODAY(),CHAR(124),"") | Q33: =IF(Q$8=TODAY(),CHAR(124),"") | R33: =IF(R$8=TODAY(),CHAR(124),"") | S33: =IF(S$8=TODAY(),CHAR(124),"") | T33: =IF(T$8=TODAY(),CHAR(124),"") | U33: =IF(U$8=TODAY(),CHAR(124),"") | V33: =IF(V$8=TODAY(),CHAR(124),"") | W33: =IF(W$8=TODAY(),CHAR(124),"") | ... EX33: =IF(EX$8=TODAY(),CHAR(124),"")
B34: 2.2.3. | C34: Бюджетная система | D34: Женя | E34: 46149 | F34: =NETWORKDAYS(E34,G34,Праздники!$A$1:$A$14) -> 2 | G34: 46150 | H34: 1 | I34: EA | J34: VD | M34: Budgt system ER diagram | P34: =IF(P$8=TODAY(),CHAR(124),"") | Q34: =IF(Q$8=TODAY(),CHAR(124),"") | R34: =IF(R$8=TODAY(),CHAR(124),"") | S34: =IF(S$8=TODAY(),CHAR(124),"") | T34: =IF(T$8=TODAY(),CHAR(124),"") | U34: =IF(U$8=TODAY(),CHAR(124),"") | V34: =IF(V$8=TODAY(),CHAR(124),"") | W34: =IF(W$8=TODAY(),CHAR(124),"") | ... EX34: =IF(EX$8=TODAY(),CHAR(124),"")
B35: 2.2.3.1 | C35: Бюджетная система - доработки после тестирования | E35: 46204 | F35: =NETWORKDAYS(E35,G35,Праздники!$A$1:$A$14) -> 55 | G35: 46280 | H35: 0.4 | I35: EA | J35: VD | N35: Last changes Update
B36: 2.3. | C36: Описание цепочек обработки данных | D36: А. Колесов | E36: 46147 | F36: =NETWORKDAYS(E36,G36,Праздники!$A$1:$A$14) -> 4 | G36: 46150 | H36: 1 | I36: Akol | J36: VD | M36: Общий процесс HC Tracker\sequence hc tracker v4.docx | P36: =IF(P$8=TODAY(),CHAR(124),"") | Q36: =IF(Q$8=TODAY(),CHAR(124),"") | R36: =IF(R$8=TODAY(),CHAR(124),"") | S36: =IF(S$8=TODAY(),CHAR(124),"") | T36: =IF(T$8=TODAY(),CHAR(124),"") | U36: =IF(U$8=TODAY(),CHAR(124),"") | V36: =IF(V$8=TODAY(),CHAR(124),"") | W36: =IF(W$8=TODAY(),CHAR(124),"") | ... EX36: =IF(EX$8=TODAY(),CHAR(124),"")
B37: 2.4. | C37: Проектирование ролевой модели | D37: Женя, Вася | E37: 46149 | F37: =NETWORKDAYS(E37,G37,Праздники!$A$1:$A$14) -> 12 | G37: 46167 | H37: 1 | I37: EA | J37: VD | O37: Женя выложит в удобном формате | P37: =IF(P$8=TODAY(),CHAR(124),"") | Q37: =IF(Q$8=TODAY(),CHAR(124),"") | R37: =IF(R$8=TODAY(),CHAR(124),"") | S37: =IF(S$8=TODAY(),CHAR(124),"") | T37: =IF(T$8=TODAY(),CHAR(124),"") | U37: =IF(U$8=TODAY(),CHAR(124),"") | V37: =IF(V$8=TODAY(),CHAR(124),"") | W37: =IF(W$8=TODAY(),CHAR(124),"") | ... EX37: =IF(EX$8=TODAY(),CHAR(124),"")
B38: 2.5. | C38: Интеграция между системами | D38: Женя, Вася | E38: 46154 | F38: =NETWORKDAYS(E38,G38,Праздники!$A$1:$A$14) -> 4 | G38: 46157 | H38: 1 | I38: EA, VD | P38: =IF(P$8=TODAY(),CHAR(124),"") | Q38: =IF(Q$8=TODAY(),CHAR(124),"") | R38: =IF(R$8=TODAY(),CHAR(124),"") | S38: =IF(S$8=TODAY(),CHAR(124),"") | T38: =IF(T$8=TODAY(),CHAR(124),"") | U38: =IF(U$8=TODAY(),CHAR(124),"") | V38: =IF(V$8=TODAY(),CHAR(124),"") | W38: =IF(W$8=TODAY(),CHAR(124),"") | ... EX38: =IF(EX$8=TODAY(),CHAR(124),"")
B39: 2.5.1. | C39: Загрузка данных HRPT в HC трекер | D39: Женя, Вася | E39: 46154 | F39: =NETWORKDAYS(E39,G39,Праздники!$A$1:$A$14) -> 10 | G39: 46167 | H39: 1 | I39: EA | J39: VD | M39: HC Tracker Cube | P39: =IF(P$8=TODAY(),CHAR(124),"") | Q39: =IF(Q$8=TODAY(),CHAR(124),"") | R39: =IF(R$8=TODAY(),CHAR(124),"") | S39: =IF(S$8=TODAY(),CHAR(124),"") | T39: =IF(T$8=TODAY(),CHAR(124),"") | U39: =IF(U$8=TODAY(),CHAR(124),"") | V39: =IF(V$8=TODAY(),CHAR(124),"") | W39: =IF(W$8=TODAY(),CHAR(124),"") | ... EX39: =IF(EX$8=TODAY(),CHAR(124),"")
B40: 2.5.2. | C40: Процессинг данных HCMC в HC трекер | D40: Женя, Вася, А. Коршунов | E40: 46156 | F40: =NETWORKDAYS(E40,G40,Праздники!$A$1:$A$14) -> 86 | G40: 46276 | H40: 0.9 | I40: EA, Akol | J40: VD | N40: Подготовить документ/схему | P40: =IF(P$8=TODAY(),CHAR(124),"") | Q40: =IF(Q$8=TODAY(),CHAR(124),"") | R40: =IF(R$8=TODAY(),CHAR(124),"") | S40: =IF(S$8=TODAY(),CHAR(124),"") | T40: =IF(T$8=TODAY(),CHAR(124),"") | U40: =IF(U$8=TODAY(),CHAR(124),"") | V40: =IF(V$8=TODAY(),CHAR(124),"") | W40: =IF(W$8=TODAY(),CHAR(124),"") | ... EX40: =IF(EX$8=TODAY(),CHAR(124),"")
B41: 2.5.3. | C41: Процессинг данных HC трекер в Бюджет | D41: Женя, Вася | E41: 46154 | F41: =NETWORKDAYS(E41,G41,Праздники!$A$1:$A$14) -> 88 | G41: 46276 | H41: 0.9 | I41: EA | J41: VD | N41: Подготовить документ/схему | P41: =IF(P$8=TODAY(),CHAR(124),"") | Q41: =IF(Q$8=TODAY(),CHAR(124),"") | R41: =IF(R$8=TODAY(),CHAR(124),"") | S41: =IF(S$8=TODAY(),CHAR(124),"") | T41: =IF(T$8=TODAY(),CHAR(124),"") | U41: =IF(U$8=TODAY(),CHAR(124),"") | V41: =IF(V$8=TODAY(),CHAR(124),"") | W41: =IF(W$8=TODAY(),CHAR(124),"") | ... EX41: =IF(EX$8=TODAY(),CHAR(124),"")
B42: 2.5.4. | C42: Загрузка факта из HRPT в Бюджет | D42: Женя, Вася | E42: 46156 | F42: =NETWORKDAYS(E42,G42,Праздники!$A$1:$A$14) -> 86 | G42: 46276 | H42: 0.5 | I42: EA | J42: VD | N42: Оценка целесообразности данного шага | O42: Есть ли задача сравнения номиналов с версией бюджета/прогноза? | P42: =IF(P$8=TODAY(),CHAR(124),"") | Q42: =IF(Q$8=TODAY(),CHAR(124),"") | R42: =IF(R$8=TODAY(),CHAR(124),"") | S42: =IF(S$8=TODAY(),CHAR(124),"") | T42: =IF(T$8=TODAY(),CHAR(124),"") | U42: =IF(U$8=TODAY(),CHAR(124),"") | V42: =IF(V$8=TODAY(),CHAR(124),"") | W42: =IF(W$8=TODAY(),CHAR(124),"") | ... EX42: =IF(EX$8=TODAY(),CHAR(124),"")
B43: 2.5.5. | C43: Загрузка факта из 1С в Бюджет | D43: Женя, Вася, Юра, Игорь | E43: 46156 | F43: =NETWORKDAYS(E43,G43,Праздники!$A$1:$A$14) -> 2 | G43: 46157 | H43: 1 | I43: VD, YuR, IK, Ach | J43: VD | K43: EA | L43: EA | M43: JOURNAL_ENTRIES_1С - проводки | P43: =IF(P$8=TODAY(),CHAR(124),"") | Q43: =IF(Q$8=TODAY(),CHAR(124),"") | R43: =IF(R$8=TODAY(),CHAR(124),"") | S43: =IF(S$8=TODAY(),CHAR(124),"") | T43: =IF(T$8=TODAY(),CHAR(124),"") | U43: =IF(U$8=TODAY(),CHAR(124),"") | V43: =IF(V$8=TODAY(),CHAR(124),"") | W43: =IF(W$8=TODAY(),CHAR(124),"") | ... EX43: =IF(EX$8=TODAY(),CHAR(124),"")
B44: 2.5.6. | C44: Загрузка факта из финансовой системы (comp, non-comp) | D44: Женя, Вася, Юра | E44: 46156 | F44: =NETWORKDAYS(E44,G44,Праздники!$A$1:$A$14) -> 2 | G44: 46157 | H44: 1 | I44: EA, YuR | J44: VD | N44: Женя выложит документ | P44: =IF(P$8=TODAY(),CHAR(124),"") | Q44: =IF(Q$8=TODAY(),CHAR(124),"") | R44: =IF(R$8=TODAY(),CHAR(124),"") | S44: =IF(S$8=TODAY(),CHAR(124),"") | T44: =IF(T$8=TODAY(),CHAR(124),"") | U44: =IF(U$8=TODAY(),CHAR(124),"") | V44: =IF(V$8=TODAY(),CHAR(124),"") | W44: =IF(W$8=TODAY(),CHAR(124),"") | ... EX44: =IF(EX$8=TODAY(),CHAR(124),"")
B45: 2.6. | C45: Интерфейсы HC-трекера и бюджетной системы | D45: Женя, Юра, Лена | E45: 46154 | F45: =NETWORKDAYS(E45,G45,Праздники!$A$1:$A$14) -> 88 | G45: =G47 -> 46276 | H45: =AVERAGE(H46:H47) -> 0.7 | I45: EA, YuR, EE | P45: =IF(P$8=TODAY(),CHAR(124),"") | Q45: =IF(Q$8=TODAY(),CHAR(124),"") | R45: =IF(R$8=TODAY(),CHAR(124),"") | S45: =IF(S$8=TODAY(),CHAR(124),"") | T45: =IF(T$8=TODAY(),CHAR(124),"") | U45: =IF(U$8=TODAY(),CHAR(124),"") | V45: =IF(V$8=TODAY(),CHAR(124),"") | W45: =IF(W$8=TODAY(),CHAR(124),"") | ... EX45: =IF(EX$8=TODAY(),CHAR(124),"")
B46: 2.6.1 | C46: Проектирование интерфейсов HC-трекера и бюджетной системы | E46: 46154 | F46: =NETWORKDAYS(E46,G46,Праздники!$A$1:$A$14) -> 4 | G46: 46157 | H46: 1 | I46: EA, YuR, EE | J46: VD | M46: HC Tracker\Мастер -файл
B47: 2.6.1 | C47: Доработки после тестирования | E47: 46258 | F47: =NETWORKDAYS(E47,G47,Праздники!$A$1:$A$14) -> 15 | G47: 46276 | H47: 0.4 | I47: EA | J47: VD
B48: результат | C48: Подготовлен функциональный дизайн | D48: Вася | E48: 46157 | F48: =NETWORKDAYS(E48,G48,Праздники!$A$1:$A$14) -> 1 | G48: 46157 | H48: 1 | I48: VD | P48: =IF(P$8=TODAY(),CHAR(124),"") | Q48: =IF(Q$8=TODAY(),CHAR(124),"") | R48: =IF(R$8=TODAY(),CHAR(124),"") | S48: =IF(S$8=TODAY(),CHAR(124),"") | T48: =IF(T$8=TODAY(),CHAR(124),"") | U48: =IF(U$8=TODAY(),CHAR(124),"") | V48: =IF(V$8=TODAY(),CHAR(124),"") | W48: =IF(W$8=TODAY(),CHAR(124),"") | ... EX48: =IF(EX$8=TODAY(),CHAR(124),"")
B49: 3. Разработка и тестирование | E49: 46146 | F49: =NETWORKDAYS(E49,G49,Праздники!$A$1:$A$14) -> 53 | G49: 46222 | P49: =IF(P$8=TODAY(),CHAR(124),"") | Q49: =IF(Q$8=TODAY(),CHAR(124),"") | R49: =IF(R$8=TODAY(),CHAR(124),"") | S49: =IF(S$8=TODAY(),CHAR(124),"") | T49: =IF(T$8=TODAY(),CHAR(124),"") | U49: =IF(U$8=TODAY(),CHAR(124),"") | V49: =IF(V$8=TODAY(),CHAR(124),"") | W49: =IF(W$8=TODAY(),CHAR(124),"") | ... EX49: =IF(EX$8=TODAY(),CHAR(124),"")
B50: 3.1. | C50: HC трекер | E50: 46146 | F50: =NETWORKDAYS(E50,G50,Праздники!$A$1:$A$14) -> 53 | G50: 46222 | P50: =IF(P$8=TODAY(),CHAR(124),"") | Q50: =IF(Q$8=TODAY(),CHAR(124),"") | R50: =IF(R$8=TODAY(),CHAR(124),"") | S50: =IF(S$8=TODAY(),CHAR(124),"") | T50: =IF(T$8=TODAY(),CHAR(124),"") | U50: =IF(U$8=TODAY(),CHAR(124),"") | V50: =IF(V$8=TODAY(),CHAR(124),"") | W50: =IF(W$8=TODAY(),CHAR(124),"") | ... EX50: =IF(EX$8=TODAY(),CHAR(124),"")
B51: 3.1.1. | C51: Подсистема управления версиями | D51: Женя | E51: 46146 | F51: =NETWORKDAYS(E51,G51,Праздники!$A$1:$A$14) -> 5 | G51: 46150 | H51: 1 | I51: EA | J51: YuR | M51: HC Tracker\Мастер -файл | P51: =IF(P$8=TODAY(),CHAR(124),"") | Q51: =IF(Q$8=TODAY(),CHAR(124),"") | R51: =IF(R$8=TODAY(),CHAR(124),"") | S51: =IF(S$8=TODAY(),CHAR(124),"") | T51: =IF(T$8=TODAY(),CHAR(124),"") | U51: =IF(U$8=TODAY(),CHAR(124),"") | V51: =IF(V$8=TODAY(),CHAR(124),"") | W51: =IF(W$8=TODAY(),CHAR(124),"") | ... EX51: =IF(EX$8=TODAY(),CHAR(124),"")
B52: 3.1.2. | C52: Основной модуль | D52: Женя | E52: 46167 | F52: =NETWORKDAYS(E52,G52,Праздники!$A$1:$A$14) -> 74 | G52: 46269 | H52: 0.8 | I52: EA | J52: YuR | M52: HC Tracker\Мастер -файл | P52: =IF(P$8=TODAY(),CHAR(124),"") | Q52: =IF(Q$8=TODAY(),CHAR(124),"") | R52: =IF(R$8=TODAY(),CHAR(124),"") | S52: =IF(S$8=TODAY(),CHAR(124),"") | T52: =IF(T$8=TODAY(),CHAR(124),"") | U52: =IF(U$8=TODAY(),CHAR(124),"") | V52: =IF(V$8=TODAY(),CHAR(124),"") | W52: =IF(W$8=TODAY(),CHAR(124),"") | ... EX52: =IF(EX$8=TODAY(),CHAR(124),"")
B53: 3.1.3. | C53: Подсистема загрузки данных HRPT в HC трекер | D53: Женя | E53: 46167 | F53: =NETWORKDAYS(E53,G53,Праздники!$A$1:$A$14) -> 18 | G53: 46191 | H53: 1 | I53: EA | J53: YuR | M53: HC Tracker\Мастер -файл | P53: =IF(P$8=TODAY(),CHAR(124),"") | Q53: =IF(Q$8=TODAY(),CHAR(124),"") | R53: =IF(R$8=TODAY(),CHAR(124),"") | S53: =IF(S$8=TODAY(),CHAR(124),"") | T53: =IF(T$8=TODAY(),CHAR(124),"") | U53: =IF(U$8=TODAY(),CHAR(124),"") | V53: =IF(V$8=TODAY(),CHAR(124),"") | W53: =IF(W$8=TODAY(),CHAR(124),"") | ... EX53: =IF(EX$8=TODAY(),CHAR(124),"")
B54: 3.1.4. | C54: Подсиcтема процессинга данных HCMC | D54: Женя | E54: 46167 | F54: =NETWORKDAYS(E54,G54,Праздники!$A$1:$A$14) -> 18 | G54: 46191 | H54: 1 | I54: EA | J54: YuR | M54: HC Tracker\Мастер -файл | N54: =C72 -> Интеграция с HC-трекером (триггер запуска процессинга) | P54: =IF(P$8=TODAY(),CHAR(124),"") | Q54: =IF(Q$8=TODAY(),CHAR(124),"") | R54: =IF(R$8=TODAY(),CHAR(124),"") | S54: =IF(S$8=TODAY(),CHAR(124),"") | T54: =IF(T$8=TODAY(),CHAR(124),"") | U54: =IF(U$8=TODAY(),CHAR(124),"") | V54: =IF(V$8=TODAY(),CHAR(124),"") | W54: =IF(W$8=TODAY(),CHAR(124),"") | ... EX54: =IF(EX$8=TODAY(),CHAR(124),"")
B55: 3.1.5. | C55: Отчетность | D55: Женя | E55: 46167 | F55: =NETWORKDAYS(E55,G55,Праздники!$A$1:$A$14) -> 29 | G55: 46208 | H55: 0.5 | I55: EA | P55: =IF(P$8=TODAY(),CHAR(124),"") | Q55: =IF(Q$8=TODAY(),CHAR(124),"") | R55: =IF(R$8=TODAY(),CHAR(124),"") | S55: =IF(S$8=TODAY(),CHAR(124),"") | T55: =IF(T$8=TODAY(),CHAR(124),"") | U55: =IF(U$8=TODAY(),CHAR(124),"") | V55: =IF(V$8=TODAY(),CHAR(124),"") | W55: =IF(W$8=TODAY(),CHAR(124),"") | ... EX55: =IF(EX$8=TODAY(),CHAR(124),"")
B56: 3.1.5.1 | C56: Подготовка куба | D56: Женя | E56: 46167 | F56: =NETWORKDAYS(E56,G56,Праздники!$A$1:$A$14) -> 22 | G56: 46197 | H56: 1 | I56: EA | J56: YuR | M56: HC Tracker\Куб и отчетность
B57: 3.1.5.2 | C57: Сборка отчетности | D57: Юра, Аня, Женя | E57: 46198 | F57: =NETWORKDAYS(E57,G57,Праздники!$A$1:$A$14) -> 57 | G57: 46276 | H57: 0.3 | I57: YuR, AO | J57: YuR | K57: EA
B58: 3.1.6. | C58: Тестирование внутреннее | D58: Юра, Лена, Аня | E58: 46193 | F58: =NETWORKDAYS(E58,G58,Праздники!$A$1:$A$14) -> 50 | G58: 46264 | H58: 1 | I58: YuR, AO | J58: YuR | P58: =IF(P$8=TODAY(),CHAR(124),"") | Q58: =IF(Q$8=TODAY(),CHAR(124),"") | R58: =IF(R$8=TODAY(),CHAR(124),"") | S58: =IF(S$8=TODAY(),CHAR(124),"") | T58: =IF(T$8=TODAY(),CHAR(124),"") | U58: =IF(U$8=TODAY(),CHAR(124),"") | V58: =IF(V$8=TODAY(),CHAR(124),"") | W58: =IF(W$8=TODAY(),CHAR(124),"") | ... EX58: =IF(EX$8=TODAY(),CHAR(124),"")
B59: 3.1.6.1 | C59: Разработка сценарев тестирования | E59: 46193 | F59: =NETWORKDAYS(E59,G59,Праздники!$A$1:$A$14) -> 5 | G59: 46199 | H59: 1 | I59: AKol | J59: VD | L59: AO, YuR | M59: Сценарии тестирования HC Tracker и HCMC last version.docx
B60: 3.1.6.2 | C60: Доработка по итогам тестирования | E60: 46259 | F60: =NETWORKDAYS(E60,G60,Праздники!$A$1:$A$14) -> 14 | G60: 46276 | H60: 0.4 | I60: EA | J60: YuR
B61: 3.1.7. | C61: Тестирование HR BP | D61: HR BP | E61: 46276 | F61: =NETWORKDAYS(E61,G61,Праздники!$A$1:$A$14) -> 6 | G61: 46283 | H61: 0 | I61: Advisory | J61: VD | K61: YuR, Akol | N61: Отправить форму на тестирование HRBP
B62: 3.1.7.1 | C62: Доработка по итогам тестирования | E62: 46276 | F62: =NETWORKDAYS(E62,G62,Праздники!$A$1:$A$14) -> 6 | G62: 46283 | H62: 0 | I62: EA | J62: Advisory
B63: 3.1.8 | C63: Размещение HC трекера в продуктив - Промышленное тестирования (без учачстия HRBP) | E63: 46283 | F63: =NETWORKDAYS(E63,G63,Праздники!$A$1:$A$14) -> 21 | G63: 46313 | H63: 0 | I63: YuR | J63: VD | K63: Akor, Akol, AO, EA, VD | L63: Akor, Akol, AO, EA, VD
B64: результат | C64: Разработан HC трекер с возможностью ввода данных, интеграцией с формами HCMC и отчетами для нового периметра | D64: Юра | E64: 46185 | F64: =NETWORKDAYS(E64,G64,Праздники!$A$1:$A$14) -> 25 | G64: 46222 | H64: 0.8 | I64: YuR | J64: DZh | K64: VD, EA, AO | P64: =IF(P$8=TODAY(),CHAR(124),"") | Q64: =IF(Q$8=TODAY(),CHAR(124),"") | R64: =IF(R$8=TODAY(),CHAR(124),"") | S64: =IF(S$8=TODAY(),CHAR(124),"") | T64: =IF(T$8=TODAY(),CHAR(124),"") | U64: =IF(U$8=TODAY(),CHAR(124),"") | V64: =IF(V$8=TODAY(),CHAR(124),"") | W64: =IF(W$8=TODAY(),CHAR(124),"") | ... EX64: =IF(EX$8=TODAY(),CHAR(124),"")
B65: 3.2. | C65: HCMC | E65: 46153 | F65: =NETWORKDAYS(E65,G65,Праздники!$A$1:$A$14) -> 48 | G65: 46222 | P65: =IF(P$8=TODAY(),CHAR(124),"") | Q65: =IF(Q$8=TODAY(),CHAR(124),"") | R65: =IF(R$8=TODAY(),CHAR(124),"") | S65: =IF(S$8=TODAY(),CHAR(124),"") | T65: =IF(T$8=TODAY(),CHAR(124),"") | U65: =IF(U$8=TODAY(),CHAR(124),"") | V65: =IF(V$8=TODAY(),CHAR(124),"") | W65: =IF(W$8=TODAY(),CHAR(124),"") | ... EX65: =IF(EX$8=TODAY(),CHAR(124),"")
B66: 3.2.1. | C66: Стартовая страница (список форм, команды создания форм) | D66: А. Коршунов | E66: 46153 | F66: =NETWORKDAYS(E66,G66,Праздники!$A$1:$A$14) -> 10 | G66: 46167 | H66: 1 | I66: AKor | P66: =IF(P$8=TODAY(),CHAR(124),"") | Q66: =IF(Q$8=TODAY(),CHAR(124),"") | R66: =IF(R$8=TODAY(),CHAR(124),"") | S66: =IF(S$8=TODAY(),CHAR(124),"") | T66: =IF(T$8=TODAY(),CHAR(124),"") | U66: =IF(U$8=TODAY(),CHAR(124),"") | V66: =IF(V$8=TODAY(),CHAR(124),"") | W66: =IF(W$8=TODAY(),CHAR(124),"") | ... EX66: =IF(EX$8=TODAY(),CHAR(124),"")
B67: 3.2.2. | C67: HCMC-формы | D67: А. Коршунов | E67: 46167 | F67: =NETWORKDAYS(E67,G67,Праздники!$A$1:$A$14) -> 14 | G67: 46184 | I67: AKor | K67: YuR | P67: =IF(P$8=TODAY(),CHAR(124),"") | Q67: =IF(Q$8=TODAY(),CHAR(124),"") | R67: =IF(R$8=TODAY(),CHAR(124),"") | S67: =IF(S$8=TODAY(),CHAR(124),"") | T67: =IF(T$8=TODAY(),CHAR(124),"") | U67: =IF(U$8=TODAY(),CHAR(124),"") | V67: =IF(V$8=TODAY(),CHAR(124),"") | W67: =IF(W$8=TODAY(),CHAR(124),"") | ... EX67: =IF(EX$8=TODAY(),CHAR(124),"")
B68: 3.2.2.1. | C68: HC Authorisation | D68: А. Коршунов | E68: 46167 | F68: =NETWORKDAYS(E68,G68,Праздники!$A$1:$A$14) -> 5 | G68: 46171 | H68: 1 | I68: AKor | K68: YuR | P68: =IF(P$8=TODAY(),CHAR(124),"") | Q68: =IF(Q$8=TODAY(),CHAR(124),"") | R68: =IF(R$8=TODAY(),CHAR(124),"") | S68: =IF(S$8=TODAY(),CHAR(124),"") | T68: =IF(T$8=TODAY(),CHAR(124),"") | U68: =IF(U$8=TODAY(),CHAR(124),"") | V68: =IF(V$8=TODAY(),CHAR(124),"") | W68: =IF(W$8=TODAY(),CHAR(124),"") | ... EX68: =IF(EX$8=TODAY(),CHAR(124),"")
B69: 3.2.2.2. | C69: Change table | D69: А. Коршунов | E69: 46167 | F69: =NETWORKDAYS(E69,G69,Праздники!$A$1:$A$14) -> 14 | G69: 46184 | H69: 1 | I69: AKor | K69: YuR | P69: =IF(P$8=TODAY(),CHAR(124),"") | Q69: =IF(Q$8=TODAY(),CHAR(124),"") | R69: =IF(R$8=TODAY(),CHAR(124),"") | S69: =IF(S$8=TODAY(),CHAR(124),"") | T69: =IF(T$8=TODAY(),CHAR(124),"") | U69: =IF(U$8=TODAY(),CHAR(124),"") | V69: =IF(V$8=TODAY(),CHAR(124),"") | W69: =IF(W$8=TODAY(),CHAR(124),"") | ... EX69: =IF(EX$8=TODAY(),CHAR(124),"")
B70: 3.2.2.3. | C70: Offer Authorization | D70: А. Коршунов | E70: 46174 | F70: =NETWORKDAYS(E70,G70,Праздники!$A$1:$A$14) -> 9 | G70: 46184 | H70: 1 | I70: AKor | K70: YuR | P70: =IF(P$8=TODAY(),CHAR(124),"") | Q70: =IF(Q$8=TODAY(),CHAR(124),"") | R70: =IF(R$8=TODAY(),CHAR(124),"") | S70: =IF(S$8=TODAY(),CHAR(124),"") | T70: =IF(T$8=TODAY(),CHAR(124),"") | U70: =IF(U$8=TODAY(),CHAR(124),"") | V70: =IF(V$8=TODAY(),CHAR(124),"") | W70: =IF(W$8=TODAY(),CHAR(124),"") | ... EX70: =IF(EX$8=TODAY(),CHAR(124),"")
B71: 3.2.2.4. | C71: Mass transfer | D71: А. Коршунов | E71: 46182 | F71: =NETWORKDAYS(E71,G71,Праздники!$A$1:$A$14) -> 3 | G71: 46184 | H71: 0.9 | I71: AKor | K71: YuR
B72: 3.2.3. | C72: Интеграция с HC-трекером (триггер запуска процессинга) | D72: tbd | E72: 46174 | F72: 2 | G72: 46188 | H72: 1 | I72: EA | K72: YuR | O72: Дублирует шаг 3.1.4 (можем удалить?)
B73: 3.2.4. | C73: Тестирование внутреннее | D73: А. Колесов, HRIS | E73: 46197 | F73: =NETWORKDAYS(E73,G73,Праздники!$A$1:$A$14) -> 10 | G73: 46210 | H73: 1 | I73: AKol, VD, EA, Akor | J73: AKol, VD, EA, Akor | K73: YuR | P73: =IF(P$8=TODAY(),CHAR(124),"") | Q73: =IF(Q$8=TODAY(),CHAR(124),"") | R73: =IF(R$8=TODAY(),CHAR(124),"") | S73: =IF(S$8=TODAY(),CHAR(124),"") | T73: =IF(T$8=TODAY(),CHAR(124),"") | U73: =IF(U$8=TODAY(),CHAR(124),"") | V73: =IF(V$8=TODAY(),CHAR(124),"") | W73: =IF(W$8=TODAY(),CHAR(124),"") | ... EX73: =IF(EX$8=TODAY(),CHAR(124),"")
B74: 3.2.4.1 | C74: Доработка по итогам тестирования | E74: 46259 | F74: =NETWORKDAYS(E74,G74,Праздники!$A$1:$A$14) -> 14 | G74: 46276 | H74: 0.4 | I74: AKor | J74: YuR | K74: YuR
B75: 3.2.5 | C75: Тестирование HR BP | D75: HR BP | E75: 46244 | F75: 25 | G75: 46276 | H75: 0.7 | I75: Advisory | J75: Advisory | K75: YuR, Akol
B76: 3.2.5.1 | C76: Доработка по итогам тестирования | E76: 46276 | F76: =NETWORKDAYS(E76,G76,Праздники!$A$1:$A$14) -> 6 | G76: 46283 | H76: 0 | I76: AKor | K76: YuR
B77: результат | C77: Web-формы HCMC с возможностью экспорта | D77: А. Колесов | E77: 46251 | F77: =NETWORKDAYS(E77,G77,Праздники!$A$1:$A$14) -> 1 | G77: 46251 | H77: 1 | I77: Akol | J77: VD, Akor | L77: YuR | M77: HCMC forms | P77: =IF(P$8=TODAY(),CHAR(124),"") | Q77: =IF(Q$8=TODAY(),CHAR(124),"") | R77: =IF(R$8=TODAY(),CHAR(124),"") | S77: =IF(S$8=TODAY(),CHAR(124),"") | T77: =IF(T$8=TODAY(),CHAR(124),"") | U77: =IF(U$8=TODAY(),CHAR(124),"") | V77: =IF(V$8=TODAY(),CHAR(124),"") | W77: =IF(W$8=TODAY(),CHAR(124),"") | ... EX77: =IF(EX$8=TODAY(),CHAR(124),"")
B78: 3.3. | C78: Бюджет | E78: 46146 | F78: =NETWORKDAYS(E78,G78,Праздники!$A$1:$A$14) -> 51 | G78: 46218 | P78: =IF(P$8=TODAY(),CHAR(124),"") | Q78: =IF(Q$8=TODAY(),CHAR(124),"") | R78: =IF(R$8=TODAY(),CHAR(124),"") | S78: =IF(S$8=TODAY(),CHAR(124),"") | T78: =IF(T$8=TODAY(),CHAR(124),"") | U78: =IF(U$8=TODAY(),CHAR(124),"") | V78: =IF(V$8=TODAY(),CHAR(124),"") | W78: =IF(W$8=TODAY(),CHAR(124),"") | ... EX78: =IF(EX$8=TODAY(),CHAR(124),"")
B79: 3.3.1. | C79: Подсистема управления версиями | D79: Женя | E79: 46146 | F79: =NETWORKDAYS(E79,G79,Праздники!$A$1:$A$14) -> 5 | G79: 46150 | H79: 1 | I79: EA | J79: VD | M79: Budget\MasterFile | P79: =IF(P$8=TODAY(),CHAR(124),"") | Q79: =IF(Q$8=TODAY(),CHAR(124),"") | R79: =IF(R$8=TODAY(),CHAR(124),"") | S79: =IF(S$8=TODAY(),CHAR(124),"") | T79: =IF(T$8=TODAY(),CHAR(124),"") | U79: =IF(U$8=TODAY(),CHAR(124),"") | V79: =IF(V$8=TODAY(),CHAR(124),"") | W79: =IF(W$8=TODAY(),CHAR(124),"") | ... EX79: =IF(EX$8=TODAY(),CHAR(124),"")
B80: 3.3.2. | C80: Подсистема загрузки исходных данных | D80: Женя | E80: 46174 | F80: =NETWORKDAYS(E80,G80,Праздники!$A$1:$A$14) -> 10 | G80: 46188 | I80: EA | M80: Budget\MasterFile | P80: =IF(P$8=TODAY(),CHAR(124),"") | Q80: =IF(Q$8=TODAY(),CHAR(124),"") | R80: =IF(R$8=TODAY(),CHAR(124),"") | S80: =IF(S$8=TODAY(),CHAR(124),"") | T80: =IF(T$8=TODAY(),CHAR(124),"") | U80: =IF(U$8=TODAY(),CHAR(124),"") | V80: =IF(V$8=TODAY(),CHAR(124),"") | W80: =IF(W$8=TODAY(),CHAR(124),"") | ... EX80: =IF(EX$8=TODAY(),CHAR(124),"")
B81: 3.3.2.1. | C81: Демографические данные (HC трекер, HRPT) | D81: Женя | E81: 46223 | F81: =NETWORKDAYS(E81,G81,Праздники!$A$1:$A$14) -> 40 | G81: 46276 | H81: 0.5 | I81: EA | J81: YuR, EE, AO | M81: Budget\MasterFile | P81: =IF(P$8=TODAY(),CHAR(124),"") | Q81: =IF(Q$8=TODAY(),CHAR(124),"") | R81: =IF(R$8=TODAY(),CHAR(124),"") | S81: =IF(S$8=TODAY(),CHAR(124),"") | T81: =IF(T$8=TODAY(),CHAR(124),"") | U81: =IF(U$8=TODAY(),CHAR(124),"") | V81: =IF(V$8=TODAY(),CHAR(124),"") | W81: =IF(W$8=TODAY(),CHAR(124),"") | ... EX81: =IF(EX$8=TODAY(),CHAR(124),"")
B82: 3.3.2.2. | C82: Компенсационные данные - финансовый факт | D82: Женя | E82: 46174 | F82: =NETWORKDAYS(E82,G82,Праздники!$A$1:$A$14) -> 10 | G82: 46188 | H82: 1 | I82: EA | J82: YuR, EE, AO | M82: Budget\MasterFile | P82: =IF(P$8=TODAY(),CHAR(124),"") | Q82: =IF(Q$8=TODAY(),CHAR(124),"") | R82: =IF(R$8=TODAY(),CHAR(124),"") | S82: =IF(S$8=TODAY(),CHAR(124),"") | T82: =IF(T$8=TODAY(),CHAR(124),"") | U82: =IF(U$8=TODAY(),CHAR(124),"") | V82: =IF(V$8=TODAY(),CHAR(124),"") | W82: =IF(W$8=TODAY(),CHAR(124),"") | ... EX82: =IF(EX$8=TODAY(),CHAR(124),"")
B83: 3.3.2.2. | C83: Компенсационные данные - данные HR (проводки из 1С) | D83: Женя, Юра, Андрей, Игорь,Саша Колесов | E83: 46174 | F83: =NETWORKDAYS(E83,G83,Праздники!$A$1:$A$14) -> 74 | G83: 46276 | H83: 0.9 | I83: EA, Ik, VD | J83: YuR | M83: Budget\MasterFile
B84: 3.3.2.2.1 | C84: Настройка выгрузки мэппинга и проводок из 1С | D84: Андрей, Игорь | E84: 46188 | F84: =NETWORKDAYS(E84,G84,Праздники!$A$1:$A$14) -> 10 | G84: 46199 | H84: 1 | I84: Ach, IK | M84: Budget\MasterFile
B85: 3.3.2.2.2 | C85: Создание мэппинга счетов 1С (настройка правил трансляции из российских счетов) | D85: Юра | E85: 46191 | F85: =NETWORKDAYS(E85,G85,Праздники!$A$1:$A$14) -> 7 | G85: 46199 | H85: 1 | I85: YuR | M85: Budget\MasterFile
B86: 3.3.2.2.3 | C86: Тестирование загрузки мэппинга в HRPT | D86: Андрей, Игорь | E86: 46199 | F86: =NETWORKDAYS(E86,G86,Праздники!$A$1:$A$14) -> 6 | G86: 46206 | H86: 1 | I86: Ach, IK | M86: Budget\MasterFile
B87: 3.3.2.2.4 | C87: Проверка полноты мэппинга компонентов на финансовые счета (отдельные таблицы в продуктовое среде) | D87: Саша Колесов, Женя | E87: 46206 | F87: =NETWORKDAYS(E87,G87,Праздники!$A$1:$A$14) -> 7 | G87: 46216 | H87: 1 | I87: EA | J87: YuR | M87: Готовый отчет Форма 1.2_план-факт ФОТ
B88: 3.3.2.2.5 | C88: Загрузка факта из таблицы проводок в бюджетную систему в соответсвии с мэппингом | D88: Женя | E88: 46216 | F88: =NETWORKDAYS(E88,G88,Праздники!$A$1:$A$14) -> 5 | G88: 46220 | H88: 1 | I88: Ach | M88: Budget\MasterFile
B89: 3.3.2.3. | C89: Non-comp расходы | D89: Женя | E89: 46266 | F89: =NETWORKDAYS(E89,G89,Праздники!$A$1:$A$14) -> 22 | G89: 46295 | H89: =AVERAGE(H90:H92) -> 0.66666667 | I89: EA | J89: YuR, EE, AO | N89: Провести встречу по процессу бюджетирования noncomp расходов | P89: =IF(P$8=TODAY(),CHAR(124),"") | Q89: =IF(Q$8=TODAY(),CHAR(124),"") | R89: =IF(R$8=TODAY(),CHAR(124),"") | S89: =IF(S$8=TODAY(),CHAR(124),"") | T89: =IF(T$8=TODAY(),CHAR(124),"") | U89: =IF(U$8=TODAY(),CHAR(124),"") | V89: =IF(V$8=TODAY(),CHAR(124),"") | W89: =IF(W$8=TODAY(),CHAR(124),"") | ... EX89: =IF(EX$8=TODAY(),CHAR(124),"")
B90: 3.3.2.3.1 | C90: Формы для загрузки в бюджетную систему | E90: 46269 | F90: =NETWORKDAYS(E90,G90,Праздники!$A$1:$A$14) -> 6 | G90: 46276 | H90: 1 | I90: EA | J90: YuR | K90: EE, VD, AO
B91: 3.3.2.3.2 | C91: Дизайн отчетной формы для пользователя | E91: 46269 | F91: =NETWORKDAYS(E91,G91,Праздники!$A$1:$A$14) -> 6 | G91: 46276 | H91: 1 | I91: YuR, AO | J91: YuR, EE, AO | M91: NonComp
B92: 3.3.2.3.3 | C92: Разработка формы в системе | E92: 46269 | F92: =NETWORKDAYS(E92,G92,Праздники!$A$1:$A$14) -> 11 | G92: 46283 | H92: 0 | I92: EA | J92: YuR, EE, AO | K92: YuR, EE, AO | N92: Провести встречу по процессу бюджетирования noncomp расходов (обсудить возможность внесения данных со стороны HR функций)
B93: 3.3.3. | C93: Изменение модели расчета отпускных | D93: Лена, Юра | E93: 46231 | F93: =NETWORKDAYS(E93,G93,Праздники!$A$1:$A$14) -> 34 | G93: 46276 | H93: 0.5 | I93: EE | J93: YuR, AO | N93: встреча EE AO YuR
B94: 3.3.3. | C94: Изменение модели расчета соцвзносов, страховки (описание) | D94: Лена, Юра | E94: 46231 | F94: =NETWORKDAYS(E94,G94,Праздники!$A$1:$A$14) -> 47 | G94: 46295 | H94: 0.6 | I94: YuR | J94: YuR, EE
B95: 3.3.3.1 | C95: Изменение модели расчета отпускных и соцвзносов, страховки (разработка) | D95: Женя | E95: 46295 | I95: EA | J95: YuR, EE, AO
B96: 3.3.4. | C96: Бюджетные формы | D96: Женя | E96: 46188 | F96: =NETWORKDAYS(E96,G96,Праздники!$A$1:$A$14) -> 5 | G96: 46192 | H96: 1 | I96: EA | J96: YuR, EE, AO | P96: =IF(P$8=TODAY(),CHAR(124),"") | Q96: =IF(Q$8=TODAY(),CHAR(124),"") | R96: =IF(R$8=TODAY(),CHAR(124),"") | S96: =IF(S$8=TODAY(),CHAR(124),"") | T96: =IF(T$8=TODAY(),CHAR(124),"") | U96: =IF(U$8=TODAY(),CHAR(124),"") | V96: =IF(V$8=TODAY(),CHAR(124),"") | W96: =IF(W$8=TODAY(),CHAR(124),"") | ... EX96: =IF(EX$8=TODAY(),CHAR(124),"")
B97: 3.3.4. | C97: Отчетность и аналитика (куб + типовые отчеты) | D97: Женя | E97: 46195 | F97: =NETWORKDAYS(E97,G97,Праздники!$A$1:$A$14) -> 5 | G97: 46199 | H97: 0.4 | I97: EA | J97: YuR, EE, AO | P97: =IF(P$8=TODAY(),CHAR(124),"") | Q97: =IF(Q$8=TODAY(),CHAR(124),"") | R97: =IF(R$8=TODAY(),CHAR(124),"") | S97: =IF(S$8=TODAY(),CHAR(124),"") | T97: =IF(T$8=TODAY(),CHAR(124),"") | U97: =IF(U$8=TODAY(),CHAR(124),"") | V97: =IF(V$8=TODAY(),CHAR(124),"") | W97: =IF(W$8=TODAY(),CHAR(124),"") | ... EX97: =IF(EX$8=TODAY(),CHAR(124),"")
B98: 3.3.4.1 | C98: Разработка куба бюджетной системы | E98: 46023 | F98: =NETWORKDAYS(E98,G98,Праздники!$A$1:$A$14) -> 115 | G98: 46199 | H98: 1 | I98: EA | J98: YuR, EE, AO | M98: Budget\MasterFile
B99: 3.3.4.2 | C99: Реализация типовых отчетных форм в системе | E99: 46272 | F99: =NETWORKDAYS(E99,G99,Праздники!$A$1:$A$14) -> 10 | G99: 46283 | H99: 0.2 | I99: EA, AO, YuR | J99: YuR, EE, DZh, SO | K99: EA | N99: Дашборд/отчетная форма на HRPT Portal
B100: 3.3.5. | C100: Тестирование | D100: Юра, Лена | E100: 46230 | F100: =NETWORKDAYS(E100,G100,Праздники!$A$1:$A$14) -> 15 | G100: 46249 | I100: YuR, EE | P100: =IF(P$8=TODAY(),CHAR(124),"") | Q100: =IF(Q$8=TODAY(),CHAR(124),"") | R100: =IF(R$8=TODAY(),CHAR(124),"") | S100: =IF(S$8=TODAY(),CHAR(124),"") | T100: =IF(T$8=TODAY(),CHAR(124),"") | U100: =IF(U$8=TODAY(),CHAR(124),"") | V100: =IF(V$8=TODAY(),CHAR(124),"") | W100: =IF(W$8=TODAY(),CHAR(124),"") | ... EX100: =IF(EX$8=TODAY(),CHAR(124),"")
B101: результат_MVP | C101: Бюджетная система, бюджетный куб, комплект типовых-отчетов | D101: Юра, Лена | E101: 46174 | F101: =NETWORKDAYS(E101,G101,Праздники!$A$1:$A$14) -> 87 | G101: 46295 | H101: 0.5 | I101: YuR, EE | J101: YuR, EE, DZh, SO | P101: =IF(P$8=TODAY(),CHAR(124),"") | Q101: =IF(Q$8=TODAY(),CHAR(124),"") | R101: =IF(R$8=TODAY(),CHAR(124),"") | S101: =IF(S$8=TODAY(),CHAR(124),"") | T101: =IF(T$8=TODAY(),CHAR(124),"") | U101: =IF(U$8=TODAY(),CHAR(124),"") | V101: =IF(V$8=TODAY(),CHAR(124),"") | W101: =IF(W$8=TODAY(),CHAR(124),"") | ... EX101: =IF(EX$8=TODAY(),CHAR(124),"")
B102: результат_Целевой | C102: Бюджетная система, бюджетный куб, комплект типовых-отчетов | D102: Юра, Лена | E102: 46174 | F102: =NETWORKDAYS(E102,G102,Праздники!$A$1:$A$14) -> 99 | G102: 46313 | H102: 0.2 | I102: YuR, EE | J102: YuR, EE, DZh, SO
...

Sheet DecisionLog
A1: РЕЕСТР РЕШЕНИЙ | Значимые решения проекта
A4: ID решения | B4: Вопрос / решение | C4: Домен | D4: Владелец решения | E4: Обязательные участники | F4: Обязательное согласование | G4: Варианты / рекомендация | H4: Срок решения | I4: Статус | J4: Принятое решение | K4: Дата решения | L4: Связанные задачи / контрольные точки | M4: Эскалация | N4: Примечание

Sheet TeamRoles
B3: Роль | C3: Участник
B4: Спонсор проекта | C4: DZh
B5: Заказчик | C5: DZh
B6: Проектный менеджер | C6: AO
B7: Методолог | C7: AO
B8: Техлид | C8: VD
B9: Техписатель | C9: VD
B10: Заказчик | C10: SO
B11: UAT | C11: SO
B12: Методолог | C12: EE
B13: Заказчик | C13: EE
B14: UAT | C14: EE
... B21: Поддержка проекта | C21: EP

Sheet Праздники
A1: 46023
A2: 46024
A3: 46027
A4: 46028
A5: 46029
A6: 46030
A7: 46031
A8: 46076
A9: 46090
A10: 46143
A11: 46153
A12: 46185
... A14: 46387
