Workbook

Sheet Обложка
B2: Факторный анализ затрат на персонал — сквозные числовые примеры
B3: Приложение к документу «Методология факторного анализа», v2.0 · август 2026 · проект «Бюджетная система по затратам на персонал»
B5: Ключевые результаты моделирования
B6: Показатель | C6: Пример 1 · Год к году | D6: Пример 2 · Бюджет vs Форкаст
B7: База сравнения (факт PY / бюджет), руб/год | C7: ='Пример 1 · Год к году'!O7 | D7: ='Пример 2 · Бюджет vs Форкаст'!O7
B8: Анализируемая версия (прогноз CY / форкаст), руб/год | C8: ='Пример 1 · Год к году'!O8 | D8: ='Пример 2 · Бюджет vs Форкаст'!O8
B9: Отклонение, руб/год | C9: ='Пример 1 · Год к году'!O9 | D9: ='Пример 2 · Бюджет vs Форкаст'!O9
B10: Сумма факторов (контроль), руб/год | C10: ='Пример 1 · Год к году'!O40 | D10: ='Пример 2 · Бюджет vs Форкаст'!O25
B13: Состав файла
B14: Лист | C14: Содержание
B15: Пример 1 · Год к году | C15: Сотрудник А: найм/повышение/увольнение в PY, повторный найм/повышение/декрет в CY. Оконная логика: CY-факторы — «с месяца события до конца года», PY-факторы — reverse YTD
B16: Пример 2 · Бюджет vs Форкаст | C16: Вакансия B (бюджет) vs найм и увольнение сотрудника C (форкаст). Логика «сторно/реализация», агрегированный водопад с drill-down
B19: Условные обозначения и допущения
B20: • Синий шрифт — входные данные; чёрный — формулы; зелёный — ссылки на другие листы.
B21: • Конвенция месяца события: увольнение фиксируется в первом месяце отсутствия Person ID в срезе; уход в декрет — в месяце смены статуса Active → LTL (запись сохраняется, оклад = 0).
B22: • Все факторы считаются только по окладной части номинала (HR-5); соцвзносы и прочие статьи FIX до появления поименного факта 1С анализируются «статья к статье».
B23: • Сумма факторов обязана сходиться с прямой дельтой версий помесячно и за год — контрольные строки «Проверка сходимости» на каждом листе.

Sheet Пример 1 · Год к году
B2: Пример 1 · Сравнение «год к году»: прогноз CY против факта PY (сотрудник А)
B3: События: найм март PY (100) → повышение сент PY (+10) → увольнение дек PY → повторный найм фев CY (130) → повышение апр CY (+15) → декрет авг CY (статус LTL)
B5: 1. Помесячные оклады (входные данные, руб/мес)
B6: Показатель | C6: Янв | D6: Фев | E6: Мар | F6: Апр | G6: Май | H6: Июн | I6: Июл | J6: Авг | K6: Сен | L6: Окт | M6: Ноя | N6: Дек | O6: Год
B7: Факт PY: оклад, руб/мес | C7: 0 | D7: 0 | E7: 100 | F7: 100 | G7: 100 | H7: 100 | I7: 100 | J7: 100 | K7: 110 | L7: 110 | M7: 110 | N7: 0 | O7: =SUM(C7:N7)
B8: Прогноз CY: оклад, руб/мес | C8: 0 | D8: 130 | E8: 130 | F8: 145 | G8: 145 | H8: 145 | I8: 145 | J8: 0 | K8: 0 | L8: 0 | M8: 0 | N8: 0 | O8: =SUM(C8:N8)
B9: Отклонение CY − PY, руб/мес | C9: =C8-C7 | D9: =D8-D7 | E9: =E8-E7 | F9: =F8-F7 | G9: =G8-G7 | H9: =H8-H7 | I9: =I8-I7 | J9: =J8-J7 | ... N9: =N8-N7 | O9: =SUM(C9:N9)
B10: Конвенция: «уволен в декабре» = на конец декабря Person ID отсутствует в срезе (декабрь — первый месяц без выплат). «Ушёл в декрет в августе» = в августе статус Active → Long-Term Leave, запись сохраняется, оклад = 0.
B12: 2. Реестр событий (идентификация по наличию Person ID и смене статуса/оклада)
B13: Событие | C13: Месяц | D13: Год | E13: Оклад до | F13: Оклад после | G13: Дельта оклада
B14: Hire — первый найм | C14: Мар | D14: PY | E14: 0 | F14: 100 | G14: =F14-E14
B15: Salary increase | C15: Сен | D15: PY | E15: 100 | F15: 110 | G15: =F15-E15
B16: Leaver — увольнение | C16: Дек | D16: PY | E16: 110 | F16: 0 | G16: =F16-E16
B17: Hire — повторный найм | C17: Фев | D17: CY | E17: 0 | F17: 130 | G17: =F17-E17
B18: Salary increase | C18: Апр | D18: CY | E18: 130 | F18: 145 | G18: =F18-E18
B19: LTL-out — уход в декрет | C19: Авг | D19: CY | E19: 145 | F19: 0 | G19: =F19-E19
B21: 3. Факторы: окна действия и годовой эффект (год-к-году: CY-факторы = «сумма с месяца события до конца года», PY-факторы = reverse YTD — только месяцы до месяца события)
B22: Фактор | C22: Событие-драйвер | D22: Окно: с мес. | E22: Окно: по мес. | F22: Ставка, руб/мес | G22: Месяцев | H22: Годовой эффект, руб
B23: F03 · Hire PY (найм март PY) | C23: Найм март PY @100 | D23: 1 | E23: 2 | F23: 100 | G23: =E23-D23+1 | H23: =F23*G23
B24: F07.2 · Salary increase PY (+10 сен PY) | C24: Повышение сент PY | D24: 1 | E24: 8 | F24: 10 | G24: =E24-D24+1 | H24: =F24*G24
B25: F04 · Leaver PY (увольнение дек PY) | C25: Увольнение дек PY @110 | D25: 1 | E25: 11 | F25: -110 | G25: =E25-D25+1 | H25: =F25*G25
B26: F01 · Hire CY (повторный найм фев CY) | C26: Найм фев CY @130 | D26: 2 | E26: 12 | F26: 130 | G26: =E26-D26+1 | H26: =F26*G26
B27: F07.1 · Salary increase CY (+15 апр CY) | C27: Повышение апр CY | D27: 4 | E27: 12 | F27: 15 | G27: =E27-D27+1 | H27: =F27*G27
B28: F11_1 · LTL start CY (уход в декрет с авг CY) | C28: Уход в декрет авг CY @145 | D28: 8 | E28: 12 | F28: -145 | G28: =E28-D28+1 | H28: =F28*G28
B29: ИТОГО сумма факторов | H29: =SUM(H23:H28)
B31: 4. Помесячная атрибуция факторов и контрольная сверка (руб/мес)
B32: Фактор \ Месяц | C32: 1 | D32: 2 | E32: 3 | F32: 4 | G32: 5 | H32: 6 | I32: 7 | J32: 8 | K32: 9 | L32: 10 | M32: 11 | N32: 12 | O32: Год
B33: ← номера месяцев (служебная строка для формул окна)
B34: F03 · Hire PY (найм март PY) | C34: =IF(AND(C$32>=$D23,C$32<=$E23),$F23,0) | D34: =IF(AND(D$32>=$D23,D$32<=$E23),$F23,0) | E34: =IF(AND(E$32>=$D23,E$32<=$E23),$F23,0) | F34: =IF(AND(F$32>=$D23,F$32<=$E23),$F23,0) | G34: =IF(AND(G$32>=$D23,G$32<=$E23),$F23,0) | H34: =IF(AND(H$32>=$D23,H$32<=$E23),$F23,0) | I34: =IF(AND(I$32>=$D23,I$32<=$E23),$F23,0) | J34: =IF(AND(J$32>=$D23,J$32<=$E23),$F23,0) | ... N34: =IF(AND(N$32>=$D23,N$32<=$E23),$F23,0) | O34: =SUM(C34:N34)
B35: F07.2 · Salary increase PY (+10 сен PY) | C35: =IF(AND(C$32>=$D24,C$32<=$E24),$F24,0) | D35: =IF(AND(D$32>=$D24,D$32<=$E24),$F24,0) | E35: =IF(AND(E$32>=$D24,E$32<=$E24),$F24,0) | F35: =IF(AND(F$32>=$D24,F$32<=$E24),$F24,0) | G35: =IF(AND(G$32>=$D24,G$32<=$E24),$F24,0) | H35: =IF(AND(H$32>=$D24,H$32<=$E24),$F24,0) | I35: =IF(AND(I$32>=$D24,I$32<=$E24),$F24,0) | J35: =IF(AND(J$32>=$D24,J$32<=$E24),$F24,0) | ... N35: =IF(AND(N$32>=$D24,N$32<=$E24),$F24,0) | O35: =SUM(C35:N35)
B36: F04 · Leaver PY (увольнение дек PY) | C36: =IF(AND(C$32>=$D25,C$32<=$E25),$F25,0) | D36: =IF(AND(D$32>=$D25,D$32<=$E25),$F25,0) | E36: =IF(AND(E$32>=$D25,E$32<=$E25),$F25,0) | F36: =IF(AND(F$32>=$D25,F$32<=$E25),$F25,0) | G36: =IF(AND(G$32>=$D25,G$32<=$E25),$F25,0) | H36: =IF(AND(H$32>=$D25,H$32<=$E25),$F25,0) | I36: =IF(AND(I$32>=$D25,I$32<=$E25),$F25,0) | J36: =IF(AND(J$32>=$D25,J$32<=$E25),$F25,0) | ... N36: =IF(AND(N$32>=$D25,N$32<=$E25),$F25,0) | O36: =SUM(C36:N36)
B37: F01 · Hire CY (повторный найм фев CY) | C37: =IF(AND(C$32>=$D26,C$32<=$E26),$F26,0) | D37: =IF(AND(D$32>=$D26,D$32<=$E26),$F26,0) | E37: =IF(AND(E$32>=$D26,E$32<=$E26),$F26,0) | F37: =IF(AND(F$32>=$D26,F$32<=$E26),$F26,0) | G37: =IF(AND(G$32>=$D26,G$32<=$E26),$F26,0) | H37: =IF(AND(H$32>=$D26,H$32<=$E26),$F26,0) | I37: =IF(AND(I$32>=$D26,I$32<=$E26),$F26,0) | J37: =IF(AND(J$32>=$D26,J$32<=$E26),$F26,0) | ... N37: =IF(AND(N$32>=$D26,N$32<=$E26),$F26,0) | O37: =SUM(C37:N37)
B38: F07.1 · Salary increase CY (+15 апр CY) | C38: =IF(AND(C$32>=$D27,C$32<=$E27),$F27,0) | D38: =IF(AND(D$32>=$D27,D$32<=$E27),$F27,0) | E38: =IF(AND(E$32>=$D27,E$32<=$E27),$F27,0) | F38: =IF(AND(F$32>=$D27,F$32<=$E27),$F27,0) | G38: =IF(AND(G$32>=$D27,G$32<=$E27),$F27,0) | H38: =IF(AND(H$32>=$D27,H$32<=$E27),$F27,0) | I38: =IF(AND(I$32>=$D27,I$32<=$E27),$F27,0) | J38: =IF(AND(J$32>=$D27,J$32<=$E27),$F27,0) | ... N38: =IF(AND(N$32>=$D27,N$32<=$E27),$F27,0) | O38: =SUM(C38:N38)
B39: F11_1 · LTL start CY (декрет с авг CY) | C39: =IF(AND(C$32>=$D28,C$32<=$E28),$F28,0) | D39: =IF(AND(D$32>=$D28,D$32<=$E28),$F28,0) | E39: =IF(AND(E$32>=$D28,E$32<=$E28),$F28,0) | F39: =IF(AND(F$32>=$D28,F$32<=$E28),$F28,0) | G39: =IF(AND(G$32>=$D28,G$32<=$E28),$F28,0) | H39: =IF(AND(H$32>=$D28,H$32<=$E28),$F28,0) | I39: =IF(AND(I$32>=$D28,I$32<=$E28),$F28,0) | J39: =IF(AND(J$32>=$D28,J$32<=$E28),$F28,0) | ... N39: =IF(AND(N$32>=$D28,N$32<=$E28),$F28,0) | O39: =SUM(C39:N39)
B40: Сумма факторов | C40: =SUM(C34:C39) | D40: =SUM(D34:D39) | E40: =SUM(E34:E39) | F40: =SUM(F34:F39) | G40: =SUM(G34:G39) | H40: =SUM(H34:H39) | I40: =SUM(I34:I39) | J40: =SUM(J34:J39) | ... O40: =SUM(O34:O39)
B41: Контроль: прямая дельта CY − PY | C41: =C9 | D41: =D9 | E41: =E9 | F41: =F9 | G41: =G9 | H41: =H9 | I41: =I9 | J41: =J9 | ... O41: =O9
B42: Проверка сходимости | C42: =IF(C40=C41,"OK","ОШИБКА") | D42: =IF(D40=D41,"OK","ОШИБКА") | E42: =IF(E40=E41,"OK","ОШИБКА") | F42: =IF(F40=F41,"OK","ОШИБКА") | G42: =IF(G40=G41,"OK","ОШИБКА") | H42: =IF(H40=H41,"OK","ОШИБКА") | I42: =IF(I40=I41,"OK","ОШИБКА") | J42: =IF(J40=J41,"OK","ОШИБКА") | ... O42: =IF(O40=O41,"OK","ОШИБКА")
B44: Читаемость: повторный найм даёт зеркальные факторы Leaver PY (−1 210) и Hire CY (+1 430). Они НЕ неттируются: сотрудник легитимно присутствует в двух факторах, сумма факторов (−90) точно равна прямой дельте версий (840 − 930).
B45: Нюанс: премия повторного найма (+20 к прежнему окладу 110) не выделяется отдельным фактором — она «сидит» в нетто-паре Hire CY / Leaver PY (+220 = 20 × 11 мес). Зафиксировано как известное ограничение.

Sheet Пример 2 · Бюджет vs Форкаст
B2: Пример 2 · Сравнение версий внутри года: бюджет CY против форкаста CY (логика «сторно / реализация»)
B3: Бюджет: вакансия B с февраля, 200 руб/мес. Форкаст: вакансия B отсторнирована; сотрудник C нанят в апреле на 250 руб/мес, увольняется в ноябре (ноябрь — первый месяц отсутствия)
B5: 1. Помесячные оклады версий (входные данные, руб/мес)
B6: Показатель | C6: Янв | D6: Фев | E6: Мар | F6: Апр | G6: Май | H6: Июн | I6: Июл | J6: Авг | K6: Сен | L6: Окт | M6: Ноя | N6: Дек | O6: Год
B7: Бюджет CY: вакансия B, руб/мес | C7: 0 | D7: 200 | E7: 200 | F7: 200 | G7: 200 | H7: 200 | I7: 200 | J7: 200 | K7: 200 | L7: 200 | M7: 200 | N7: 200 | O7: =SUM(C7:N7)
B8: Форкаст CY: сотрудник C, руб/мес | C8: 0 | D8: 0 | E8: 0 | F8: 250 | G8: 250 | H8: 250 | I8: 250 | J8: 250 | K8: 250 | L8: 250 | M8: 0 | N8: 0 | O8: =SUM(C8:N8)
B9: Отклонение Форкаст − Бюджет, руб/мес | C9: =C8-C7 | D9: =D8-D7 | E9: =E8-E7 | F9: =F8-F7 | G9: =G8-G7 | H9: =H8-H7 | I9: =I8-I7 | J9: =J8-J7 | ... N9: =N8-N7 | O9: =SUM(C9:N9)
B10: Допущение: связки Vacancy ID ↔ Person ID нет — нельзя утверждать, что C «закрыл» вакансию B. Сторно вакансии и найм C показываются раздельно.
B12: 2. Факторы: бюджетные — сторно (откат запланированного), форкастные — реализация («сумма с месяца события до конца года»)
B13: Фактор | C13: Версия / знак | D13: Окно: с мес. | E13: Окно: по мес. | F13: Ставка, руб/мес | G13: Месяцев | H13: Годовой эффект, руб
B14: F05_4 · Вакансия B — СТОРНО (закрытие вакансии ТГ) | C14: Бюджет / минус | D14: 2 | E14: 12 | F14: -200 | G14: =E14-D14+1 | H14: =F14*G14
B15: F01 · Hire — найм C в форкасте (апрель) | C15: Форкаст / плюс | D15: 4 | E15: 12 | F15: 250 | G15: =E15-D15+1 | H15: =F15*G15
B16: F02 · Leaver — увольнение C в форкасте (ноябрь) | C16: Форкаст / минус | D16: 11 | E16: 12 | F16: -250 | G16: =E16-D16+1 | H16: =F16*G16
B17: ИТОГО сумма факторов | H17: =SUM(H14:H16)
B19: 3. Помесячная атрибуция факторов и контрольная сверка (руб/мес)
B20: Фактор \ Месяц | C20: 1 | D20: 2 | E20: 3 | F20: 4 | G20: 5 | H20: 6 | I20: 7 | J20: 8 | K20: 9 | L20: 10 | M20: 11 | N20: 12 | O20: Год
B21: ← номера месяцев (служебная строка для формул окна)
B22: F05_4 · Сторно вакансии B | C22: =IF(AND(C$20>=$D14,C$20<=$E14),$F14,0) | D22: =IF(AND(D$20>=$D14,D$20<=$E14),$F14,0) | E22: =IF(AND(E$20>=$D14,E$20<=$E14),$F14,0) | F22: =IF(AND(F$20>=$D14,F$20<=$E14),$F14,0) | G22: =IF(AND(G$20>=$D14,G$20<=$E14),$F14,0) | H22: =IF(AND(H$20>=$D14,H$20<=$E14),$F14,0) | I22: =IF(AND(I$20>=$D14,I$20<=$E14),$F14,0) | J22: =IF(AND(J$20>=$D14,J$20<=$E14),$F14,0) | ... N22: =IF(AND(N$20>=$D14,N$20<=$E14),$F14,0) | O22: =SUM(C22:N22)
B23: F01 · Hire C (форкаст) | C23: =IF(AND(C$20>=$D15,C$20<=$E15),$F15,0) | D23: =IF(AND(D$20>=$D15,D$20<=$E15),$F15,0) | E23: =IF(AND(E$20>=$D15,E$20<=$E15),$F15,0) | F23: =IF(AND(F$20>=$D15,F$20<=$E15),$F15,0) | G23: =IF(AND(G$20>=$D15,G$20<=$E15),$F15,0) | H23: =IF(AND(H$20>=$D15,H$20<=$E15),$F15,0) | I23: =IF(AND(I$20>=$D15,I$20<=$E15),$F15,0) | J23: =IF(AND(J$20>=$D15,J$20<=$E15),$F15,0) | ... N23: =IF(AND(N$20>=$D15,N$20<=$E15),$F15,0) | O23: =SUM(C23:N23)
B24: F02 · Leaver C (форкаст) | C24: =IF(AND(C$20>=$D16,C$20<=$E16),$F16,0) | D24: =IF(AND(D$20>=$D16,D$20<=$E16),$F16,0) | E24: =IF(AND(E$20>=$D16,E$20<=$E16),$F16,0) | F24: =IF(AND(F$20>=$D16,F$20<=$E16),$F16,0) | G24: =IF(AND(G$20>=$D16,G$20<=$E16),$F16,0) | H24: =IF(AND(H$20>=$D16,H$20<=$E16),$F16,0) | I24: =IF(AND(I$20>=$D16,I$20<=$E16),$F16,0) | J24: =IF(AND(J$20>=$D16,J$20<=$E16),$F16,0) | ... N24: =IF(AND(N$20>=$D16,N$20<=$E16),$F16,0) | O24: =SUM(C24:N24)
B25: Сумма факторов | C25: =SUM(C22:C24) | D25: =SUM(D22:D24) | E25: =SUM(E22:E24) | F25: =SUM(F22:F24) | G25: =SUM(G22:G24) | H25: =SUM(H22:H24) | I25: =SUM(I22:I24) | J25: =SUM(J22:J24) | ... O25: =SUM(O22:O24)
B26: Контроль: прямая дельта Форкаст − Бюджет | C26: =C9 | D26: =D9 | E26: =E9 | F26: =F9 | G26: =G9 | H26: =H9 | I26: =I9 | J26: =J9 | ... O26: =O9
B27: Проверка сходимости | C27: =IF(C25=C26,"OK","ОШИБКА") | D27: =IF(D25=D26,"OK","ОШИБКА") | E27: =IF(E25=E26,"OK","ОШИБКА") | F27: =IF(F25=F26,"OK","ОШИБКА") | G27: =IF(G25=G26,"OK","ОШИБКА") | H27: =IF(H25=H26,"OK","ОШИБКА") | I27: =IF(I25=I26,"OK","ОШИБКА") | J27: =IF(J25=J26,"OK","ОШИБКА") | ... O27: =IF(O25=O26,"OK","ОШИБКА")
B29: 4. Агрегированное представление для водопада (верхний уровень) с drill-down до компонентов
B30: Уровень | C30: Фактор (агрегат) | D30: Эффект, руб | E30: Drill-down: компонент | F30: Эффект, руб
B31: Агрегат | C31: Наймы (Hires) | D31: =H14+H15 | E31: Сторно вакансии B (не состоялась) | F31: =H14
E32: Hire C (фактический найм в форкасте) | F32: =H15
B33: Агрегат | C33: Увольнения (Leavers) | D33: =H16 | E33: Leaver C (не планировался в бюджете) | F33: =H16
B34: ИТОГО | C34: Отклонение форкаста от бюджета | D34: =D31+D33 | F34: =F31+F33
B36: Читаемость: найм C (+2 250) дороже вакансии B (−2 200 сторно) и смещён по срокам (апрель вместо февраля); увольнение C в ноябре — незапланированное, отдельный фактор −500. Итог −450 = 1 750 − 2 200.
B37: Если вакансия B в форкасте остаётся открытой в будущих месяцах, сторно применяется только к месяцам, по которым вакансия снята; открытые месяцы дельты не дают и фактором не являются.
